nornir_librenms/__init__.py
nornir_librenms/librenms_inventory.py
nornir_librenms/nr_config.py
nornir_librenms-0.2.0.dist-info/LICENSE
nornir_librenms-0.2.0.dist-info/WHEEL
nornir_librenms-0.2.0.dist-info/METADATA
nornir_librenms-0.2.0.dist-info/RECORD
