Metadata-Version: 2.1
Name: nornir-librenms
Version: 0.2.0
Summary: LibreNMS inventory plugin for Nornir
License: MIT
Author: Shereif ElHamalawy
Requires-Python: >=3.8,<4.0
Classifier: License :: OSI Approved :: MIT License
Classifier: Programming Language :: Python :: 3
Classifier: Programming Language :: Python :: 3.10
Classifier: Programming Language :: Python :: 3.8
Classifier: Programming Language :: Python :: 3.9
Requires-Dist: nornir (>=3.1.0,<4.0.0)
Requires-Dist: requests (>=2.26.0,<3.0.0)
